{
    "title": "Тест на понимание темы: Технология создания виртуальных частных сетей",
    "materialType": "test",
    "description": "Нажмите ``Начать прохождение`` для отображения вопросов и выберите подходящий ответ",
    "difficulty": 1,
    "duration": "PT0H30M",
    "tags": {
        "$ref": "../../material-tags.json"
    },
    "skills": {},
    "passingScore": 100,
    "assets": {
        "$ref": "./assets"
    },
    "questions": [
        {
            "question": "Какое преимущество VPN позволяет предприятию легко добавлять больше пользователей в сеть?",
            "answerType": "singleChoice",
            "answers": [
                {
                    "answer": "сокращение затрат",
                    "correct": false,
                    "comment": "VPN обеспечивают масштабируемость, которая позволяет организациям использовать Интернет, чтобы легко добавлять новых пользователей"
                },
                {
                    "answer": "информационная безопасность",
                    "correct": false,
                    "comment": "VPN обеспечивают масштабируемость, которая позволяет организациям использовать Интернет, чтобы легко добавлять новых пользователей"
                },
                {
                    "answer": "масштабируемость",
                    "correct": true
                },
                {
                    "answer": "совместимость",
                    "correct": false,
                    "comment": "VPN обеспечивают масштабируемость, которая позволяет организациям использовать Интернет, чтобы легко добавлять новых пользователей"
                }
            ]
        },
        {
            "question": "Какое преимущество VPN позволяет предприятию увеличить пропускную способность для удаленных сайтов без добавления дополнительного оборудования или каналов глобальной сети?",
            "answerType": "singleChoice",
            "answers": [
                {
                    "answer": "сокращение затрат",
                    "correct": true
                },
                {
                    "answer": "информационная безопасность",
                    "correct": false,
                    "comment": "VPN сокращают затраты на подключение для удаленных сайтов и пользователей, одновременно увеличивая пропускную способность удаленного подключения"
                },
                {
                    "answer": "масштабируемость",
                    "correct": false,
                    "comment": "VPN сокращают затраты на подключение для удаленных сайтов и пользователей, одновременно увеличивая пропускную способность удаленного подключения"
                },
                {
                    "answer": "совместимость",
                    "correct": false,
                    "comment": "VPN сокращают затраты на подключение для удаленных сайтов и пользователей, одновременно увеличивая пропускную способность удаленного подключения"
                }
            ]
        },
        {
            "question": "Какое преимущество VPN защищает данные от несанкционированного доступа благодаря усовершенствованным протоколам шифрования и аутентификации?",
            "answerType": "singleChoice",
            "answers": [
                {
                    "answer": "сокращение затрат",
                    "correct": false,
                    "comment": "Подключения VPN обеспечивают высокий уровень безопасности с помощью усовершенствованных механизмов шифрования и протоколов аутентификации, которые защищают данные от несанкционированного доступа"
                },
                {
                    "answer": "информационная безопасность",
                    "correct": true
                },
                {
                    "answer": "масштабируемость",
                    "correct": false,
                    "comment": "Подключения VPN обеспечивают высокий уровень безопасности с помощью усовершенствованных механизмов шифрования и протоколов аутентификации, которые защищают данные от несанкционированного доступа"
                },
                {
                    "answer": "совместимость",
                    "correct": false,
                    "comment": "Подключения VPN обеспечивают высокий уровень безопасности с помощью усовершенствованных механизмов шифрования и протоколов аутентификации, которые защищают данные от несанкционированного доступа"
                }
            ]
        },
        {
            "question": "Какой тип VPN используется для подключения мобильного пользователя?",
            "answerType": "singleChoice",
            "answers": [
                {
                    "answer": "Site-to-site (межузловые или межфилиальные)",
                    "correct": false,
                    "comment": "VPN с удаленным доступом создается динамически, чтобы безопасно соединенить клиента (мобильного пользователя) и оконечное устройство VPN"
                },
                {
                    "answer": "Remote-access (удаленный доступ)",
                    "correct": true
                },
                {
                    "answer": "GRE",
                    "correct": false,
                    "comment": "VPN с удаленным доступом создается динамически, чтобы безопасно соединенить клиента (мобильного пользователя) и оконечное устройство VPN"
                },
                {
                    "answer": "протокол IPsec",
                    "correct": false,
                    "comment": "VPN с удаленным доступом создается динамически, чтобы безопасно соединенить клиента (мобильного пользователя) и оконечное устройство VPN"
                }
            ]
        },
        {
            "question": "Какие решения VPN обычно используются на предприятии? (верны три варианта)",
            "answerType": "multiChoice",
            "answers": [
                {
                    "answer": "MPLS VPN уровня 2",
                    "correct": false,
                    "comment": "Управляемые предприятием корпоративные сети включают IPsec, GRE через IPsec, DMVPN, VTI, клиентский IPsec и SSL без клиента"
                },
                {
                    "answer": "MPLS VPN уровня 3",
                    "correct": false,
                    "comment": "Управляемые предприятием корпоративные сети включают IPsec, GRE через IPsec, DMVPN, VTI, клиентский IPsec и SSL без клиента"
                },
                {
                    "answer": "протокол IPsec",
                    "correct": true
                },
                {
                    "answer": "SSL",
                    "correct": true
                },
                {
                    "answer": "Frame Relay.",
                    "correct": false,
                    "comment": "Управляемые предприятием корпоративные сети включают IPsec, GRE через IPsec, DMVPN, VTI, клиентский IPsec и SSL без клиента"
                },
                {
                    "answer": "DMVPN",
                    "correct": true
                }
            ]
        }
    ]
}
