{
    "title": "Тест на понимание темы: Документация по сети",
    "materialType": "test",
    "description": "Нажмите ``Начать прохождение`` для отображения вопросов и выберите подходящий ответ",
    "difficulty": 1,
    "duration": "PT0H30M",
    "tags": {
        "$ref": "../../material-tags.json"
    },
    "skills": {},
    "passingScore": 100,
    "assets": {
        "$ref": "./assets"
    },
    "questions": [
        {
            "question": "Какая схема топологии отображает IP-адреса?",
            "answerType": "singleChoice",
            "answers": [
                {
                    "answer": "IP топология",
                    "correct": false,
                    "comment": "Диаграмма логической топологии отображает информацию об IP-адресе."
                },
                {
                    "answer": "Логическая топология",
                    "correct": true
                },
                {
                    "answer": "Физическая топология",
                    "correct": false,
                    "comment": "Диаграмма логической топологии отображает информацию об IP-адресе."
                },
                {
                    "answer": "Топология портов",
                    "correct": false,
                    "comment": "Диаграмма логической топологии отображает информацию об IP-адресе."
                }
            ]
        },
        {
            "question": "На какой документ можно ссылаться для идентификации ОС на сервере?",
            "answerType": "singleChoice",
            "answers": [
                {
                    "answer": "Документация по конечной системе",
                    "correct": true
                },
                {
                    "answer": "Документация комутационным устройствам LAN",
                    "correct": false,
                    "comment": "В документации по конечной системе будет содержаться информация о конечной системе."
                },
                {
                    "answer": "Документация по маршрутизатору",
                    "correct": false,
                    "comment": "В документации по конечной системе будет содержаться информация о конечной системе."
                }
            ]
        },
        {
            "question": "На какие вопросы отвечают базовые показатели сети? (Выберите три варианта.)",
            "answerType": "multiChoice",
            "answers": [
                {
                    "answer": "Как сеть работает в течение обычного дня?",
                    "correct": true
                },
                {
                    "answer": "Сколько стоит сеть?",
                    "correct": false,
                    "comment": "Базовые показатели сети должны показывать, как сеть работает в течение обычного дня и какие части сети наиболее и наименее часто используются."
                },
                {
                    "answer": "Каковы сетевые политики?",
                    "correct": false,
                    "comment": "Базовые показатели сети должны показывать, как сеть работает в течение обычного дня и какие части сети наиболее и наименее часто используются."
                },
                {
                    "answer": "Какая часть сети используется в наименьшей степени?",
                    "correct": true
                },
                {
                    "answer": "Какая часть сети используется наиболее интенсивно?",
                    "correct": true
                },
                {
                    "answer": "Кто отвечает за управление сетью?",
                    "correct": false,
                    "comment": "Базовые показатели сети должны показывать, как сеть работает в течение обычного дня и какие части сети наиболее и наименее часто используются."
                }
            ]
        },
        {
            "question": "Верно ли утверждение? Определение базовых показателей сети никогда не заканчивается и предполагает непрерывный ежегодный сбор информации.",
            "answerType": "singleChoice",
            "answers": [
                {
                    "answer": "Истина",
                    "correct": false,
                    "comment": "Правильный ответ — Ложь. Базовые показатели сети отражают работу сети в обычный день и указывают, какик части сети используется наиболее (или наименее) интенсивно."
                },
                {
                    "answer": "Ложь",
                    "correct": true
                }
            ]
        },
        {
            "question": "Какую команду можно использовать для получения подробной информации о напрямую подключенных соседних устройствах Cisco?",
            "answerType": "singleChoice",
            "answers": [
                {
                    "answer": "show cdp neighbor",
                    "correct": true
                },
                {
                    "answer": "show ip interface",
                    "correct": false,
                    "comment": "Команда show cdp neighbor используется для получения подробных сведений о напрямую подключенных соседних устройствах Cisco."
                },
                {
                    "answer": "show ip route",
                    "correct": false,
                    "comment": "Команда show cdp neighbor используется для получения подробных сведений о напрямую подключенных соседних устройствах Cisco."
                },
                {
                    "answer": "show version",
                    "correct": false,
                    "comment": "Команда show cdp neighbor используется для получения подробных сведений о напрямую подключенных соседних устройствах Cisco."
                }
            ]
        }
    ]
}
