{
    "title": "Работа в симуляторе: настройка расширенных списков контроля доступа (сценарий 1)",
    "shortName": "lab-5.4.12",
    "materialType": "lab",
    "description": "Цели лабораторной работы:\r\r* Настроить, применить и проверить расширенный нумерованный список контроля доступа.\r* Настроить, применить и проверить расширенный именованный список контроля доступа.",
    "difficulty": 1,
    "duration": "PT0H29M",
    "tags": {
        "$ref": "../../material-tags.json"
    },
    "credentialsSchema": {
        "userName": {
            "title": "Имя пользователя",
            "source": "learn_user"
        },
        "password": {
            "title": "Пароль",
            "source": "learn_password"
        },
        "consoleURL": {
            "title": "Адрес портала",
            "value": "https://portal.skillscloud.company"
        }
    },
    "skills": {},
    "text": {
        "$ref": "./README.md"
    },
    "assessment": {
        "$ref": "./assessment.json"
    },
    "deploy": {
        "$ref": "./deploy"
    },
    "assets": {
        "$ref": "./assets"
    }
}